{
  "main": {
    "id": "78ddb5fc7758b6da",
    "type": "split",
    "children": [
      {
        "id": "08d81a3f434171b1",
        "type": "tabs",
        "children": [
          {
            "id": "102b3fadedfa9c1e",
            "type": "leaf",
            "state": {
              "type": "markdown",
              "state": {
                "file": "docs/second brain idea.md",
                "mode": "source",
                "source": false
              },
              "icon": "lucide-file",
              "title": "second brain idea"
            }
          }
        ]
      }
    ],
    "direction": "vertical"
  },
  "left": {
    "id": "0bb894f9ba9acad1",
    "type": "split",
    "children": [
      {
        "id": "40724b3888e3e6e0",
        "type": "tabs",
        "children": [
          {
            "id": "4bf15bc84f50bbc1",
            "type": "leaf",
            "state": {
              "type": "file-explorer",
              "state": {
                "sortOrder": "alphabetical",
                "autoReveal": false
              },
              "icon": "lucide-folder-closed",
              "title": "Files"
            }
          },
          {
            "id": "0bd0aeace236dbcf",
            "type": "leaf",
            "state": {
              "type": "search",
              "state": {
                "query": "",
                "matchingCase": false,
                "explainSearch": false,
                "collapseAll": false,
                "extraContext": false,
                "sortOrder": "alphabetical"
              },
              "icon": "lucide-search",
              "title": "Search"
            }
          },
          {
            "id": "f82c958b2683012c",
            "type": "leaf",
            "state": {
              "type": "bookmarks",
              "state": {},
              "icon": "lucide-bookmark",
              "title": "Bookmarks"
            }
          }
        ]
      }
    ],
    "direction": "horizontal",
    "width": 300
  },
  "right": {
    "id": "189af3e0e19d10f2",
    "type": "split",
    "children": [
      {
        "id": "e7fb962c93f149d6",
        "type": "tabs",
        "children": [
          {
            "id": "6995fbf6be025b3b",
            "type": "leaf",
            "state": {
              "type": "backlink",
              "state": {
                "file": "2025-04-10.md",
                "collapseAll": false,
                "extraContext": false,
                "sortOrder": "alphabetical",
                "showSearch": false,
                "searchQuery": "",
                "backlinkCollapsed": false,
                "unlinkedCollapsed": true
              },
              "icon": "links-coming-in",
              "title": "Backlinks for 2025-04-10"
            }
          },
          {
            "id": "c33dc7a2115d2e99",
            "type": "leaf",
            "state": {
              "type": "outgoing-link",
              "state": {
                "file": "2025-04-10.md",
                "linksCollapsed": false,
                "unlinkedCollapsed": true
              },
              "icon": "links-going-out",
              "title": "Outgoing links from 2025-04-10"
            }
          },
          {
            "id": "ab4f59cd21fc2090",
            "type": "leaf",
            "state": {
              "type": "tag",
              "state": {
                "sortOrder": "frequency",
                "useHierarchy": true,
                "showSearch": false,
                "searchQuery": ""
              },
              "icon": "lucide-tags",
              "title": "Tags"
            }
          },
          {
            "id": "dbcd79a593bda3f7",
            "type": "leaf",
            "state": {
              "type": "outline",
              "state": {
                "file": "2025-04-10.md",
                "followCursor": false,
                "showSearch": false,
                "searchQuery": ""
              },
              "icon": "lucide-list",
              "title": "Outline of 2025-04-10"
            }
          }
        ]
      }
    ],
    "direction": "horizontal",
    "width": 300,
    "collapsed": true
  },
  "left-ribbon": {
    "hiddenItems": {
      "switcher:Open quick switcher": false,
      "graph:Open graph view": false,
      "canvas:Create new canvas": false,
      "daily-notes:Open today's daily note": false,
      "templates:Insert template": false,
      "command-palette:Open command palette": false
    }
  },
  "active": "102b3fadedfa9c1e",
  "lastOpenFiles": [
    "secondBrainSrc/thinker/src/main.rs",
    "secondBrainSrc/thinker/src/event_analyzer.rs",
    "secondBrainSrc/thinker/src",
    "secondBrainSrc/thinker",
    "secondBrainSrc/recall/src/query_engine.rs",
    "secondBrainSrc/recall/src/main.rs",
    "secondBrainSrc/recall/src/fuzzy_finder.rs",
    "secondBrainSrc/recall/src",
    "secondBrainSrc/recall",
    "secondBrainSrc/learner/src/main.rs",
    "secondBrainSrc/learner/src/keylogger.rs",
    "secondBrainSrc/demo/README.md",
    "secondBrainSrc/README.md",
    "docs/Planiel...Staniel.md",
    "docs/Ideas.md",
    "docs/second brain idea.md",
    "second brain idea.md",
    "Ideas.md",
    "Planiel...Staniel.md",
    "2025-04-10.md"
  ]
}